{"nodes": [{"id": "e_work_python_attendence_project_mapper_workflow_tracer_py", "label": "workflow_tracer.py", "file_type": "code", "source_file": "E:\\WORK\\python\\ATTENDENCE\\project_mapper\\workflow_tracer.py", "source_location": "L1"}, {"id": "workflow_tracer_trace_workflow", "label": "trace_workflow()", "file_type": "code", "source_file": "E:\\WORK\\python\\ATTENDENCE\\project_mapper\\workflow_tracer.py", "source_location": "L27"}], "edges": [{"source": "e_work_python_attendence_project_mapper_workflow_tracer_py", "target": "pathlib", "relation": "imports_from", "confidence": "EXTRACTED", "source_file": "E:\\WORK\\python\\ATTENDENCE\\project_mapper\\workflow_tracer.py", "source_location": "L1", "weight": 1.0}, {"source": "e_work_python_attendence_project_mapper_workflow_tracer_py", "target": "json", "relation": "imports", "confidence": "EXTRACTED", "source_file": "E:\\WORK\\python\\ATTENDENCE\\project_mapper\\workflow_tracer.py", "source_location": "L2", "weight": 1.0}, {"source": "e_work_python_attendence_project_mapper_workflow_tracer_py", "target": "workflow_tracer_trace_workflow", "relation": "contains", "confidence": "EXTRACTED", "source_file": "E:\\WORK\\python\\ATTENDENCE\\project_mapper\\workflow_tracer.py", "source_location": "L27", "weight": 1.0}], "raw_calls": [{"caller_nid": "workflow_tracer_trace_workflow", "callee": "set", "source_file": "E:\\WORK\\python\\ATTENDENCE\\project_mapper\\workflow_tracer.py", "source_location": "L44"}, {"caller_nid": "workflow_tracer_trace_workflow", "callee": "add", "source_file": "E:\\WORK\\python\\ATTENDENCE\\project_mapper\\workflow_tracer.py", "source_location": "L56"}, {"caller_nid": "workflow_tracer_trace_workflow", "callee": "print", "source_file": "E:\\WORK\\python\\ATTENDENCE\\project_mapper\\workflow_tracer.py", "source_location": "L65"}, {"caller_nid": "workflow_tracer_trace_workflow", "callee": "get", "source_file": "E:\\WORK\\python\\ATTENDENCE\\project_mapper\\workflow_tracer.py", "source_location": "L72"}, {"caller_nid": "workflow_tracer_trace_workflow", "callee": "print", "source_file": "E:\\WORK\\python\\ATTENDENCE\\project_mapper\\workflow_tracer.py", "source_location": "L77"}]}